MANIFEST.in
README.txt
setup.py
collective/__init__.py
collective.collage.blogging.egg-info/PKG-INFO
collective.collage.blogging.egg-info/SOURCES.txt
collective.collage.blogging.egg-info/dependency_links.txt
collective.collage.blogging.egg-info/entry_points.txt
collective.collage.blogging.egg-info/namespace_packages.txt
collective.collage.blogging.egg-info/not-zip-safe
collective.collage.blogging.egg-info/requires.txt
collective.collage.blogging.egg-info/top_level.txt
collective/collage/__init__.py
collective/collage/blogging/README.txt
collective/collage/blogging/__init__.py
collective/collage/blogging/configure.zcml
collective/collage/blogging/interfaces.py
collective/collage/blogging/tests.py
collective/collage/blogging/version.txt
collective/collage/blogging/browser/__init__.py
collective/collage/blogging/browser/blogging.pt
collective/collage/blogging/browser/configure.zcml
collective/collage/blogging/browser/utils.py
collective/collage/blogging/browser/views.py
collective/collage/blogging/profiles/default/browserlayer.xml
collective/collage/blogging/profiles/default/metadata.xml
docs/HISTORY.txt
docs/INSTALL.txt
docs/LICENSE.GPL
docs/LICENSE.txt