Metadata-Version: 1.0
Name: collective.collage.blogging
Version: 1.0
Summary: A collective.blogging integration for Products.Collage.
Home-page: http://plone.org/products/collective.collage.blogging
Author: Davi Lima
Author-email: davilima6@gmail.com
License: GPL
Platform: UNKNOWN
Classifier: Framework :: Plone
Classifier: Programming Language :: Python
